{
  "success": true,
  "timestamp": "2025-11-09T10:57:45.807801",
  "total_negative_posts": 4,
  "from_cache": false,
  "negative_posts": [
    {
      "id": 1987557812763779146,
      "text": "3x NBA YoungBoy Tickets For Tonight At\n\nVenue: T-Mobile Arena - Las Vegas, NV\n\nDate: Sunday - October 09\n\nProof: Happy to show the Screen Record of the tickets in App \n\nPrice: Negotiable Serious buyers only \n\nDM for more info - No scammers please 🙏 🤎\n\n#NBAYoungBoyTickets https://t.co/Q0KcXFU3Wo",
      "author_username": "destbeney",
      "author_name": "Destiny",
      "created_at": "2025-11-09T16:28:04+00:00",
      "likes": 0,
      "retweets": 0,
      "replies": 0,
      "url": "https://twitter.com/destbeney/status/1987557812763779146",
      "confidence_score": 0.312,
      "keywords_found": [
        "scam"
      ]
    },
    {
      "id": 1987536602696990950,
      "text": "Wts NBA Young Boy tickets for tonight at T-Mobile Arena, Las Vegas, NV\n\nWill take any reasonable price and will provide all the necessary proof\n\nWill show a screen recording down to the Ticketmaster app",
      "author_username": "rileybb17",
      "author_name": "Riley Marks",
      "created_at": "2025-11-09T15:03:47+00:00",
      "likes": 0,
      "retweets": 0,
      "replies": 0,
      "url": "https://twitter.com/rileybb17/status/1987536602696990950",
      "confidence_score": 0.312,
      "keywords_found": [
        "down"
      ]
    },
    {
      "id": 1987528154085531986,
      "text": "@TMobile @TMobileHelp @Delta @TMobileHelp why does your website stink so bad. It’s like a rabbit hole nothing works properly!! I just tried to update my autopay and it won’t refresh just keeps “thinking” absolutely horrible service!!!",
      "author_username": "tracyweeks007",
      "author_name": "Baroness",
      "created_at": "2025-11-09T14:30:13+00:00",
      "likes": 0,
      "retweets": 0,
      "replies": 1,
      "url": "https://twitter.com/tracyweeks007/status/1987528154085531986",
      "confidence_score": 0.312,
      "keywords_found": [
        "horrible service"
      ]
    },
    {
      "id": 1987526567241646496,
      "text": "The Troupe Brothers in the Ringling Bros. and Barnum &amp; Bailey Circus did an outSTANDING job! 🔥🔥👏🎪 #ringlingbros #barnumandbailey #circus #acrobatics #rope #standonshoulders #2down1up #kansascity #tmobile #teeterboard #backflip #travel #family #instagood #amazing #instagram https://t.co/lHQLRYwAvL",
      "author_username": "EnchanterDancer",
      "author_name": "EnchanterDancer",
      "created_at": "2025-11-09T14:23:54+00:00",
      "likes": 0,
      "retweets": 0,
      "replies": 0,
      "url": "https://twitter.com/EnchanterDancer/status/1987526567241646496",
      "confidence_score": 0.312,
      "keywords_found": [
        "down"
      ]
    }
  ],
  "cached_at": "2025-11-09T10:57:45.807859",
  "cache_expires_at": "2025-11-10T10:57:45.807863"
}